springserve/__init__.py
springserve/_account.py
springserve/_common.py
springserve/_deal.py
springserve/_decorators.py
springserve/_demand.py
springserve/_direct_connect.py
springserve/_object_change_messages.py
springserve/_reporting.py
springserve/_supply.py
springserve-0.8.13.dist-info/METADATA
springserve-0.8.13.dist-info/WHEEL
springserve-0.8.13.dist-info/top_level.txt
springserve-0.8.13.dist-info/RECORD
